Metadata-Version: 2.1
Name: look-and-say
Version: 0.1.1
Summary: A python module for exploring look and say sequences in the spirit of John H Conway.
Home-page: https://github.com/jonnycomes/look_and_say
Author: Jonny Comes
Author-email: jonnycomes@gmail.com
License: MIT license
Project-URL: Documentation, https://jonnycomes.github.io/look_and_say/docs/
Keywords: look_and_say
Platform: UNKNOWN
Requires-Python: >=3.6
License-File: LICENSE
